pydashlite/__init__.py
pydashlite/conftest.py
pydashlite/arrays/__init__.py
pydashlite/arrays/chunk_list.py
pydashlite/arrays/concat.py
pydashlite/arrays/duplicates.py
pydashlite/arrays/find_index.py
pydashlite/arrays/flatten.py
pydashlite/arrays/group_by.py
pydashlite/arrays/intersection.py
pydashlite/arrays/remove_empty.py
pydashlite/arrays/sum_by.py
pydashlite/arrays/union.py
pydashlite/arrays/uniq.py
pydashlite/collections/__init__.py
pydashlite/collections/at.py
pydashlite/collections/chunk.py
pydashlite/collections/get.py
pydashlite/collections/group_by.py
pydashlite/collections/head.py
pydashlite/collections/merge.py
pydashlite/collections/pick.py
pydashlite/collections/set_.py
pydashlite/collections/unset.py
pydashlite/objects/__init__.py
pydashlite/objects/chunk_dict.py
pydashlite/objects/find_key.py
pydashlite/objects/invert.py
pydashlite/objects/keys.py
pydashlite/objects/map_keys.py
pydashlite/objects/omit.py
pydashlite/objects/pick.py
pydashlite/objects/rename_keys.py
pydashlite/strings/__init__.py
pydashlite/strings/camel_case.py
pydashlite/tools/__init__.py
pydashlite/tools/extract_path_keys.py
pydashlite/tools/get_path_array.py
pydashlite/tools/is_flat.py
pydashlite/tools/is_iterable.py
pydashlite/tools/no_value.py
pydashlite-0.2.0.dist-info/LICENSE
pydashlite-0.2.0.dist-info/METADATA
pydashlite-0.2.0.dist-info/WHEEL
pydashlite-0.2.0.dist-info/top_level.txt
pydashlite-0.2.0.dist-info/RECORD
