Metadata-Version: 2.1
Name: pydashlite
Version: 0.2.0
Summary: Simple tools similar to pydash, but more specific and faster.
Home-page: https://github.com/glowlex/pydashlite
Author: glowlex
Author-email: antonioavocado777@gmail.com
License: MIT
Platform: UNKNOWN
Classifier: License :: OSI Approved :: MIT License
Classifier: Operating System :: OS Independent
Classifier: Programming Language :: Python :: 3.6
Classifier: Programming Language :: Python :: 3.7
Classifier: Programming Language :: Python :: 3.8
Classifier: Programming Language :: Python :: 3.9
Classifier: Programming Language :: Python :: 3.10
Classifier: Topic :: Software Development :: Libraries
Classifier: Topic :: Software Development :: Libraries :: Python Modules
Classifier: Topic :: Utilities
